lockpick.py
lockpick-1.0.2.dist-info/LICENSE.txt
lockpick-1.0.2.dist-info/METADATA
lockpick-1.0.2.dist-info/WHEEL
lockpick-1.0.2.dist-info/entry_points.txt
lockpick-1.0.2.dist-info/top_level.txt
lockpick-1.0.2.dist-info/RECORD
