Metadata-Version: 2.1
Name: lockpick
Version: 1.0.2
Summary: Distributed locking using Zookeeper
Home-page: https://github.com/raags/lockpick
Author: Raghu Udiyar
Author-email: raghusiddarth@gmail.com
License: MIT
Platform: UNKNOWN
Requires-Dist: kazoo (>=2.5.0)
